optosim
