Metadata-Version: 1.1
Name: optosim
Version: 0.1.0
Summary: Python package with functions for data analysis
Home-page: https://github.com/AshleySetter/optosim
Author: Ashley Setter
Author-email: A.Setter@soton.ac.uk
License: UNKNOWN
Download-URL: https://github.com/AshleySetter/optosim/archive/0.1.0.tar.gz
Platform: UNKNOWN
